fiscal/__init__.py
fiscal/abstract_bands.py
fiscal/abstract_liability.py
fiscal/allocators.py
fiscal/bands.py
fiscal/liability.py
fiscal-0.2.3.dist-info/METADATA
fiscal-0.2.3.dist-info/LICENSE
fiscal-0.2.3.dist-info/WHEEL
fiscal-0.2.3.dist-info/RECORD
