Metadata-Version: 2.1
Name: fiscal
Version: 0.2.3
Summary: 
Home-page: https://github.com/nylnd/fiscal
License: BSD-3-Clause
Author: Chris Nyland
Author-email: chris.nyland@gmail.com
Requires-Python: >=3.11,<4.0
Classifier: License :: OSI Approved :: BSD License
Classifier: Programming Language :: Python :: 3
Classifier: Programming Language :: Python :: 3.11
Requires-Dist: pytest (>=7.2.0,<8.0.0)
